README.md
setup.py
dmiparse/__init__.py
dmiparse.egg-info/PKG-INFO
dmiparse.egg-info/SOURCES.txt
dmiparse.egg-info/dependency_links.txt
dmiparse.egg-info/top_level.txt
tests/__init__.py
tests/test_dmiparse.py