Metadata-Version: 1.1
Name: dmiparse
Version: 0.2.0
Summary: Parse dmidecode into reasonable python
Home-page: https://github.com/xmonader/dmiparse
Author: Ahmed Youssef
Author-email: xmonader@gmail.com
License: UNKNOWN
Platform: UNKNOWN
Classifier: Development Status :: 2 - Pre-Alpha
Classifier: Programming Language :: Python
Classifier: Programming Language :: Python :: 2
Classifier: Programming Language :: Python :: 2.7
Classifier: Programming Language :: Python :: 3
Classifier: Programming Language :: Python :: 3.4
Classifier: Programming Language :: Python :: 3.5
